Workbook

Sheet INSTRUCTIONS
A1: MoneyBot RS60/EP40 — Paper Trading Package
A2: 30-Trading-Day Operational Workbook | Strategy FROZEN | Generated 2026-06-15
A4: STRATEGY PARAMETERS (FROZEN)
A5: RS Weight | B5: 60%
A6: EP Weight | B6: 40%
A7: Universe | B7: 134 NSE stocks
A8: Portfolio size | B8: Top 10 by composite score
A9: Rebalance cadence | B9: Every 10 trading days
A10: Stop-loss | B10: 10% below entry price — checked every morning
A11: Regime filter | B11: Policy C: Bull+Flat = trade | Bear = 100% cash
A12: Paper capital | B12: Rs.5,00,000 (Rs.50,000 per position)
A13: Paper start date | B13: 2026-06-16
A14: Paper end date | B14: 2026-07-27 (30 trading days)
A16: REGIME RULES (Policy C)
A17: Bull | B17: Nifty > 200DMA AND 50DMA > 200DMA → Hold/Enter positions
A18: Flat | B18: Nifty > 200DMA AND 50DMA ≤ 200DMA → Hold/Enter positions
A19: Bear | B19: Nifty < 200DMA → Exit ALL positions. 100% cash. Skip rebalance.
A21: SHEET GUIDE
A22: 1. INSTRUCTIONS | B22: This sheet — strategy params, color codes, sheet guide
A23: 2. Daily_Ops_Log | B23: PRIMARY daily sheet. Enter Nifty data every morning. Regime auto-classifies.
A24: 3. Position_Log | B24: Track all open positions. Enter fills. SL levels auto-calculate.
A25: 4. Trade_Log | B25: Record every completed trade (exit). P&L and return auto-calculate.
A26: 5. Rebalance_Log | B26: One row per rebalance event (Days 10, 20, 30 of paper period).
A27: 6. Monthly_Dashboard | B27: Pulls live metrics from Trade Log. No manual entry needed.
A28: 7. Slippage_Tracker | B28: Compare simulated vs actual fills. Slippage auto-calculates.
A29: 8. Daily_Checklist | B29: Print this. 10-minute morning routine. Tick boxes.
A30: 9. Rebalance_Checklist | B30: Print this. Use on every 10th trading day.
A31: 10. Emergency_Card | B31: Print this. One page. What to do when things break.
A33: COLOUR CODE KEY
A34: Blue bold text | B34: Hardcoded input — enter this value yourself
A35: Black text | B35: Formula — calculated automatically
A36: Green text | B36: Cross-sheet link — pulls from another tab
A37: Yellow background | B37: Cell requires user input every day/rebalance
A38: Green background | B38: Bull/Flat regime — OK to trade
A39: Red background | B39: Bear regime — cash only
A40: Orange background | B40: Warning / attention required

Sheet Daily_Ops_Log
A1: DAILY OPERATIONS LOG — MoneyBot RS60/EP40 | Paper Trading 2026-06-16 to 2026-07-27
A2: Enter YELLOW cells every morning before 9:10 AM. Regime auto-classifies. Rebalance days highlighted in blue.
A3: # | B3: Date | C3: Nifty Close | D3: 50-DMA (enter) | E3: 200-DMA (enter) | F3: 50>200? | G3: Regime | H3: Portfolio Value (Rs) | I3: Daily P&L (Rs) | J3: SL Exits (symbols) | K3: Regime Exit? | L3: Rebalance Day? | M3: Notes
A4: 1 | B4: 46189 | F4: =IF(D4=""," ",IF(D4>E4,"YES","NO")) | G4: =IF(C4="","—",IF(C4<E4,"BEAR",IF(D4>E4,"BULL","FLAT"))) | H4: 5000 | I4: — | K4: — | L4: —
A5: 2 | B5: 46190 | F5: =IF(D5=""," ",IF(D5>E5,"YES","NO")) | G5: =IF(C5="","—",IF(C5<E5,"BEAR",IF(D5>E5,"BULL","FLAT"))) | I5: =IF(H5="","",H5-H4) | K5: — | L5: —
A6: 3 | B6: 46191 | F6: =IF(D6=""," ",IF(D6>E6,"YES","NO")) | G6: =IF(C6="","—",IF(C6<E6,"BEAR",IF(D6>E6,"BULL","FLAT"))) | I6: =IF(H6="","",H6-H5) | K6: — | L6: —
A7: 4 | B7: 46192 | F7: =IF(D7=""," ",IF(D7>E7,"YES","NO")) | G7: =IF(C7="","—",IF(C7<E7,"BEAR",IF(D7>E7,"BULL","FLAT"))) | I7: =IF(H7="","",H7-H6) | K7: — | L7: —
A8: 5 | B8: 46195 | F8: =IF(D8=""," ",IF(D8>E8,"YES","NO")) | G8: =IF(C8="","—",IF(C8<E8,"BEAR",IF(D8>E8,"BULL","FLAT"))) | I8: =IF(H8="","",H8-H7) | K8: — | L8: —
A9: 6 | B9: 46196 | F9: =IF(D9=""," ",IF(D9>E9,"YES","NO")) | G9: =IF(C9="","—",IF(C9<E9,"BEAR",IF(D9>E9,"BULL","FLAT"))) | I9: =IF(H9="","",H9-H8) | K9: — | L9: —
A10: 7 | B10: 46197 | F10: =IF(D10=""," ",IF(D10>E10,"YES","NO")) | G10: =IF(C10="","—",IF(C10<E10,"BEAR",IF(D10>E10,"BULL","FLAT"))) | I10: =IF(H10="","",H10-H9) | K10: — | L10: —
A11: 8 | B11: 46198 | F11: =IF(D11=""," ",IF(D11>E11,"YES","NO")) | G11: =IF(C11="","—",IF(C11<E11,"BEAR",IF(D11>E11,"BULL","FLAT"))) | I11: =IF(H11="","",H11-H10) | K11: — | L11: —
A12: 9 | B12: 46199 | F12: =IF(D12=""," ",IF(D12>E12,"YES","NO")) | G12: =IF(C12="","—",IF(C12<E12,"BEAR",IF(D12>E12,"BULL","FLAT"))) | I12: =IF(H12="","",H12-H11) | K12: — | L12: —
A13: 10 | B13: 46202 | F13: =IF(D13=""," ",IF(D13>E13,"YES","NO")) | G13: =IF(C13="","—",IF(C13<E13,"BEAR",IF(D13>E13,"BULL","FLAT"))) | I13: =IF(H13="","",H13-H12) | K13: — | L13: REBAL
A14: 11 | B14: 46203 | F14: =IF(D14=""," ",IF(D14>E14,"YES","NO")) | G14: =IF(C14="","—",IF(C14<E14,"BEAR",IF(D14>E14,"BULL","FLAT"))) | I14: =IF(H14="","",H14-H13) | K14: — | L14: —
A15: 12 | B15: 46204 | F15: =IF(D15=""," ",IF(D15>E15,"YES","NO")) | G15: =IF(C15="","—",IF(C15<E15,"BEAR",IF(D15>E15,"BULL","FLAT"))) | I15: =IF(H15="","",H15-H14) | K15: — | L15: —
A16: 13 | B16: 46205 | F16: =IF(D16=""," ",IF(D16>E16,"YES","NO")) | G16: =IF(C16="","—",IF(C16<E16,"BEAR",IF(D16>E16,"BULL","FLAT"))) | I16: =IF(H16="","",H16-H15) | K16: — | L16: —
... A33: 30 | B33: 46230 | F33: =IF(D33=""," ",IF(D33>E33,"YES","NO")) | G33: =IF(C33="","—",IF(C33<E33,"BEAR",IF(D33>E33,"BULL","FLAT"))) | I33: =IF(H33="","",H33-H32) | K33: — | L33: REBAL
A36: CURRENT REGIME (2026-06-15): BEAR — Nifty 23,623 < 200DMA 24,921 Hold cash. Do not enter positions until Nifty reclaims 200DMA.

Sheet Position_Log
A1: POSITION LOG — Open Positions | Updated daily after market close
A2: Enter Symbol, Entry Date, Entry Price, Qty in YELLOW. SL Level, P&L, and Days Held auto-calculate. Remove row when position is closed (record it in Trade Log first).
A3: Symbol | B3: Entry Date | C3: Entry Price (Rs) | D3: Qty (shares) | E3: SL Level (auto) | F3: Current Close (Rs) | G3: Unreal. P&L (Rs) | H3: Unreal. P&L % | I3: Days Held | J3: Allocation (Rs) | K3: Status
E4: =IF(C4="","",C4*0.90) | G4: =IF(OR(C4="",D4="",F4=""),"",(F4-C4)*D4) | H4: =IF(OR(C4="",F4=""),"",F4/C4-1) | I4: =IF(B4="","",TODAY()-B4) | J4: =IF(OR(C4="",D4=""),"",C4*D4) | K4: =IF(C4="","",IF(F4="","Awaiting price",IF(F4<=E4,"*** SL TRIGGERED ***",IF(F4/C4-1<-0.07,"APPROACHING SL","OPEN"))))
E5: =IF(C5="","",C5*0.90) | G5: =IF(OR(C5="",D5="",F5=""),"",(F5-C5)*D5) | H5: =IF(OR(C5="",F5=""),"",F5/C5-1) | I5: =IF(B5="","",TODAY()-B5) | J5: =IF(OR(C5="",D5=""),"",C5*D5) | K5: =IF(C5="","",IF(F5="","Awaiting price",IF(F5<=E5,"*** SL TRIGGERED ***",IF(F5/C5-1<-0.07,"APPROACHING SL","OPEN"))))
E6: =IF(C6="","",C6*0.90) | G6: =IF(OR(C6="",D6="",F6=""),"",(F6-C6)*D6) | H6: =IF(OR(C6="",F6=""),"",F6/C6-1) | I6: =IF(B6="","",TODAY()-B6) | J6: =IF(OR(C6="",D6=""),"",C6*D6) | K6: =IF(C6="","",IF(F6="","Awaiting price",IF(F6<=E6,"*** SL TRIGGERED ***",IF(F6/C6-1<-0.07,"APPROACHING SL","OPEN"))))
E7: =IF(C7="","",C7*0.90) | G7: =IF(OR(C7="",D7="",F7=""),"",(F7-C7)*D7) | H7: =IF(OR(C7="",F7=""),"",F7/C7-1) | I7: =IF(B7="","",TODAY()-B7) | J7: =IF(OR(C7="",D7=""),"",C7*D7) | K7: =IF(C7="","",IF(F7="","Awaiting price",IF(F7<=E7,"*** SL TRIGGERED ***",IF(F7/C7-1<-0.07,"APPROACHING SL","OPEN"))))
E8: =IF(C8="","",C8*0.90) | G8: =IF(OR(C8="",D8="",F8=""),"",(F8-C8)*D8) | H8: =IF(OR(C8="",F8=""),"",F8/C8-1) | I8: =IF(B8="","",TODAY()-B8) | J8: =IF(OR(C8="",D8=""),"",C8*D8) | K8: =IF(C8="","",IF(F8="","Awaiting price",IF(F8<=E8,"*** SL TRIGGERED ***",IF(F8/C8-1<-0.07,"APPROACHING SL","OPEN"))))
E9: =IF(C9="","",C9*0.90) | G9: =IF(OR(C9="",D9="",F9=""),"",(F9-C9)*D9) | H9: =IF(OR(C9="",F9=""),"",F9/C9-1) | I9: =IF(B9="","",TODAY()-B9) | J9: =IF(OR(C9="",D9=""),"",C9*D9) | K9: =IF(C9="","",IF(F9="","Awaiting price",IF(F9<=E9,"*** SL TRIGGERED ***",IF(F9/C9-1<-0.07,"APPROACHING SL","OPEN"))))
E10: =IF(C10="","",C10*0.90) | G10: =IF(OR(C10="",D10="",F10=""),"",(F10-C10)*D10) | H10: =IF(OR(C10="",F10=""),"",F10/C10-1) | I10: =IF(B10="","",TODAY()-B10) | J10: =IF(OR(C10="",D10=""),"",C10*D10) | K10: =IF(C10="","",IF(F10="","Awaiting price",IF(F10<=E10,"*** SL TRIGGERED ***",IF(F10/C10-1<-0.07,"APPROACHING SL","OPEN"))))
E11: =IF(C11="","",C11*0.90) | G11: =IF(OR(C11="",D11="",F11=""),"",(F11-C11)*D11) | H11: =IF(OR(C11="",F11=""),"",F11/C11-1) | I11: =IF(B11="","",TODAY()-B11) | J11: =IF(OR(C11="",D11=""),"",C11*D11) | K11: =IF(C11="","",IF(F11="","Awaiting price",IF(F11<=E11,"*** SL TRIGGERED ***",IF(F11/C11-1<-0.07,"APPROACHING SL","OPEN"))))
E12: =IF(C12="","",C12*0.90) | G12: =IF(OR(C12="",D12="",F12=""),"",(F12-C12)*D12) | H12: =IF(OR(C12="",F12=""),"",F12/C12-1) | I12: =IF(B12="","",TODAY()-B12) | J12: =IF(OR(C12="",D12=""),"",C12*D12) | K12: =IF(C12="","",IF(F12="","Awaiting price",IF(F12<=E12,"*** SL TRIGGERED ***",IF(F12/C12-1<-0.07,"APPROACHING SL","OPEN"))))
E13: =IF(C13="","",C13*0.90) | G13: =IF(OR(C13="",D13="",F13=""),"",(F13-C13)*D13) | H13: =IF(OR(C13="",F13=""),"",F13/C13-1) | I13: =IF(B13="","",TODAY()-B13) | J13: =IF(OR(C13="",D13=""),"",C13*D13) | K13: =IF(C13="","",IF(F13="","Awaiting price",IF(F13<=E13,"*** SL TRIGGERED ***",IF(F13/C13-1<-0.07,"APPROACHING SL","OPEN"))))
A15: POSITION SUMMARY
A16: Total open positions | C16: =COUNTA(A4:A13)
A17: Total invested (Rs) | C17: =IFERROR(SUMPRODUCT((C4:C13<>"")*C4:C13*D4:D13),0)
A18: Total unrealised P&L (Rs) | C18: =IFERROR(SUM(G4:G13),0)
A19: Positions approaching SL (loss >7%) | C19: =COUNTIF(K4:K13,"APPROACHING SL")
A20: Positions SL triggered | C20: =COUNTIF(K4:K13,"*** SL TRIGGERED ***")

Sheet Trade_Log
A1: TRADE LOG — Completed Trades | One row per exit
A2: Enter YELLOW cells when a position is closed. Gross P&L, Net P&L, Return %, and Hold Days auto-calculate. Costs = Brokerage (Rs.20 each way) + STT 0.1% on sell side + Exchange fee 0.00345%.
A3: # | B3: Symbol | C3: Entry Date | D3: Exit Date | E3: Entry Price (Rs) | F3: Exit Price (Rs) | G3: Qty | H3: Gross P&L (Rs) | I3: Total Costs (Rs) | J3: Net P&L (Rs) | K3: Return % | L3: Hold Days | M3: Exit Reason | N3: Win?
A4: =IF(B4="","",ROW()-3) | H4: =IF(OR(E4="",F4="",G4=""),"",(F4-E4)*G4) | I4: =IF(OR(E4="",F4="",G4=""),"",40+0.001*F4*G4+0.0000345*(E4+F4)*G4) | J4: =IF(H4="","",H4-I4) | K4: =IF(OR(E4="",F4=""),"",F4/E4-1) | L4: =IF(OR(C4="",D4=""),"",D4-C4) | N4: =IF(J4="","",IF(J4>0,"WIN","LOSS"))
A5: =IF(B5="","",ROW()-3) | H5: =IF(OR(E5="",F5="",G5=""),"",(F5-E5)*G5) | I5: =IF(OR(E5="",F5="",G5=""),"",40+0.001*F5*G5+0.0000345*(E5+F5)*G5) | J5: =IF(H5="","",H5-I5) | K5: =IF(OR(E5="",F5=""),"",F5/E5-1) | L5: =IF(OR(C5="",D5=""),"",D5-C5) | N5: =IF(J5="","",IF(J5>0,"WIN","LOSS"))
A6: =IF(B6="","",ROW()-3) | H6: =IF(OR(E6="",F6="",G6=""),"",(F6-E6)*G6) | I6: =IF(OR(E6="",F6="",G6=""),"",40+0.001*F6*G6+0.0000345*(E6+F6)*G6) | J6: =IF(H6="","",H6-I6) | K6: =IF(OR(E6="",F6=""),"",F6/E6-1) | L6: =IF(OR(C6="",D6=""),"",D6-C6) | N6: =IF(J6="","",IF(J6>0,"WIN","LOSS"))
A7: =IF(B7="","",ROW()-3) | H7: =IF(OR(E7="",F7="",G7=""),"",(F7-E7)*G7) | I7: =IF(OR(E7="",F7="",G7=""),"",40+0.001*F7*G7+0.0000345*(E7+F7)*G7) | J7: =IF(H7="","",H7-I7) | K7: =IF(OR(E7="",F7=""),"",F7/E7-1) | L7: =IF(OR(C7="",D7=""),"",D7-C7) | N7: =IF(J7="","",IF(J7>0,"WIN","LOSS"))
A8: =IF(B8="","",ROW()-3) | H8: =IF(OR(E8="",F8="",G8=""),"",(F8-E8)*G8) | I8: =IF(OR(E8="",F8="",G8=""),"",40+0.001*F8*G8+0.0000345*(E8+F8)*G8) | J8: =IF(H8="","",H8-I8) | K8: =IF(OR(E8="",F8=""),"",F8/E8-1) | L8: =IF(OR(C8="",D8=""),"",D8-C8) | N8: =IF(J8="","",IF(J8>0,"WIN","LOSS"))
A9: =IF(B9="","",ROW()-3) | H9: =IF(OR(E9="",F9="",G9=""),"",(F9-E9)*G9) | I9: =IF(OR(E9="",F9="",G9=""),"",40+0.001*F9*G9+0.0000345*(E9+F9)*G9) | J9: =IF(H9="","",H9-I9) | K9: =IF(OR(E9="",F9=""),"",F9/E9-1) | L9: =IF(OR(C9="",D9=""),"",D9-C9) | N9: =IF(J9="","",IF(J9>0,"WIN","LOSS"))
A10: =IF(B10="","",ROW()-3) | H10: =IF(OR(E10="",F10="",G10=""),"",(F10-E10)*G10) | I10: =IF(OR(E10="",F10="",G10=""),"",40+0.001*F10*G10+0.0000345*(E10+F10)*G10) | J10: =IF(H10="","",H10-I10) | K10: =IF(OR(E10="",F10=""),"",F10/E10-1) | L10: =IF(OR(C10="",D10=""),"",D10-C10) | N10: =IF(J10="","",IF(J10>0,"WIN","LOSS"))
A11: =IF(B11="","",ROW()-3) | H11: =IF(OR(E11="",F11="",G11=""),"",(F11-E11)*G11) | I11: =IF(OR(E11="",F11="",G11=""),"",40+0.001*F11*G11+0.0000345*(E11+F11)*G11) | J11: =IF(H11="","",H11-I11) | K11: =IF(OR(E11="",F11=""),"",F11/E11-1) | L11: =IF(OR(C11="",D11=""),"",D11-C11) | N11: =IF(J11="","",IF(J11>0,"WIN","LOSS"))
A12: =IF(B12="","",ROW()-3) | H12: =IF(OR(E12="",F12="",G12=""),"",(F12-E12)*G12) | I12: =IF(OR(E12="",F12="",G12=""),"",40+0.001*F12*G12+0.0000345*(E12+F12)*G12) | J12: =IF(H12="","",H12-I12) | K12: =IF(OR(E12="",F12=""),"",F12/E12-1) | L12: =IF(OR(C12="",D12=""),"",D12-C12) | N12: =IF(J12="","",IF(J12>0,"WIN","LOSS"))
A13: =IF(B13="","",ROW()-3) | H13: =IF(OR(E13="",F13="",G13=""),"",(F13-E13)*G13) | I13: =IF(OR(E13="",F13="",G13=""),"",40+0.001*F13*G13+0.0000345*(E13+F13)*G13) | J13: =IF(H13="","",H13-I13) | K13: =IF(OR(E13="",F13=""),"",F13/E13-1) | L13: =IF(OR(C13="",D13=""),"",D13-C13) | N13: =IF(J13="","",IF(J13>0,"WIN","LOSS"))
A14: =IF(B14="","",ROW()-3) | H14: =IF(OR(E14="",F14="",G14=""),"",(F14-E14)*G14) | I14: =IF(OR(E14="",F14="",G14=""),"",40+0.001*F14*G14+0.0000345*(E14+F14)*G14) | J14: =IF(H14="","",H14-I14) | K14: =IF(OR(E14="",F14=""),"",F14/E14-1) | L14: =IF(OR(C14="",D14=""),"",D14-C14) | N14: =IF(J14="","",IF(J14>0,"WIN","LOSS"))
A15: =IF(B15="","",ROW()-3) | H15: =IF(OR(E15="",F15="",G15=""),"",(F15-E15)*G15) | I15: =IF(OR(E15="",F15="",G15=""),"",40+0.001*F15*G15+0.0000345*(E15+F15)*G15) | J15: =IF(H15="","",H15-I15) | K15: =IF(OR(E15="",F15=""),"",F15/E15-1) | L15: =IF(OR(C15="",D15=""),"",D15-C15) | N15: =IF(J15="","",IF(J15>0,"WIN","LOSS"))
... A33: =IF(B33="","",ROW()-3) | H33: =IF(OR(E33="",F33="",G33=""),"",(F33-E33)*G33) | I33: =IF(OR(E33="",F33="",G33=""),"",40+0.001*F33*G33+0.0000345*(E33+F33)*G33) | J33: =IF(H33="","",H33-I33) | K33: =IF(OR(E33="",F33=""),"",F33/E33-1) | L33: =IF(OR(C33="",D33=""),"",D33-C33) | N33: =IF(J33="","",IF(J33>0,"WIN","LOSS"))
A35: TRADE SUMMARY (auto-updates)
A36: Total trades | B36: =COUNTA(B4:B33)
A37: Winning trades | B37: =COUNTIF(N4:N33,"WIN")
A38: Losing trades | B38: =COUNTIF(N4:N33,"LOSS")
A39: Win rate | B39: =IFERROR(B37/B36,"")
A40: Total gross P&L (Rs) | B40: =IFERROR(SUM(H4:H33),"")
A41: Total costs (Rs) | B41: =IFERROR(SUM(I4:I33),"")
A42: Total net P&L (Rs) | B42: =IFERROR(SUM(J4:J33),"")
A43: Gross wins (Rs) | B43: =IFERROR(SUMIF(H4:H33,">"&0,H4:H33),"")
A44: Gross losses (Rs) | B44: =IFERROR(SUMIF(H4:H33,"<"&0,H4:H33),"")
A45: Profit Factor | B45: =IFERROR(B43/ABS(B44),"")
A46: Average win % (per trade) | B46: =IFERROR(AVERAGEIF(N4:N33,"WIN",K4:K33),"")
A47: Average loss % (per trade) | B47: =IFERROR(AVERAGEIF(N4:N33,"LOSS",K4:K33),"")
A48: Average hold days | B48: =IFERROR(AVERAGE(L4:L33),"")
A49: Exits by SL | B49: =COUNTIF(M4:M33,"SL")
A50: Exits by Rebalance | B50: =COUNTIF(M4:M33,"Rebalance")
A51: Exits by Regime | B51: =COUNTIF(M4:M33,"Regime")

Sheet Rebalance_Log
A1: REBALANCE LOG — One row per rebalance event
A2: Paper trading has 3 rebalance days: Day 10 (2026-06-27), Day 20 (2026-07-10), Day 30 (2026-07-24). Enter Exits, Entries, and Holds as comma-separated symbols.
A3: # | B3: Date | C3: Regime | D3: Skipped? | E3: Top-10 Selected (symbol : score) | F3: Exits (comma-separated) | G3: Entries (comma-separated) | H3: Cash Before (Rs) | I3: Cash After (Rs) | J3: Turnover (%)
A4: 1 | B4: 46202 | D4: NO
A5: 2 | B5: 46216 | D5: NO
A6: 3 | B6: 46230 | D6: NO
A8: HOW TO RECORD A REBALANCE: (1) Enter regime. (2) If Bear, set Skipped=YES and stop. (3) Run final_validation.py — paste the top-10 symbols+scores in col E. (4) List stocks you sold in col F (not in new top-10). (5) List stocks you bought in col G (new in top-10). (6) Enter cash balance before/after fills. (7) Estimate turnover = (shares sold + shares bought) / (2 x total shares) x 100.

Sheet Monthly_Dashboard
A1: MONTHLY PERFORMANCE DASHBOARD — MoneyBot RS60/EP40
A2: Pulls live from Trade_Log and Daily_Ops_Log. Enter the Nifty benchmark return in yellow. All other cells are formulas.
A4: PORTFOLIO PERFORMANCE
A5: Paper Start Capital (Rs) | B5: 500000
A6: Current Portfolio Value (Rs) | B6: =IF(COUNTA(Daily_Ops_Log!H4:H33)>0,LOOKUP(2,1/(Daily_Ops_Log!H4:H33<>""),Daily_Ops_Log!H4:H33),500000)
A7: Total Net P&L (Rs) | B7: =IFERROR(SUM(Trade_Log!J4:J33),0)
A8: Period Return % | B8: =IFERROR((B6-B5)/B5,0)
A9: Nifty Period Return % (enter)
A10: Alpha vs Nifty (pp) | B10: =IF(OR(B8="",B9=""),"",B8-B9)
A12: TRADE QUALITY
A13: Total trades completed | B13: =IFERROR(Trade_Log!B36,0)
A14: Winning trades | B14: =IFERROR(Trade_Log!B37,0)
A15: Losing trades | B15: =IFERROR(Trade_Log!B38,0)
A16: Win rate % | B16: =IFERROR(Trade_Log!B39,0)
A17: Profit Factor | B17: =IFERROR(Trade_Log!B45,"")
A18: Average win % | B18: =IFERROR(Trade_Log!B46,"")
A19: Average loss % | B19: =IFERROR(Trade_Log!B47,"")
A20: Average hold days | B20: =IFERROR(Trade_Log!B48,"")
A22: COST ANALYSIS
A23: Total costs paid (Rs) | B23: =IFERROR(SUM(Trade_Log!I4:I33),0)
A24: Costs as % of start capital | B24: =IFERROR(B23/B5,0)
A25: Avg slippage per trade (enter)
A27: REGIME BREAKDOWN (30 days)
A28: Days in BULL regime | B28: =COUNTIF(Daily_Ops_Log!G4:G33,"BULL")
A29: Days in FLAT regime | B29: =COUNTIF(Daily_Ops_Log!G4:G33,"FLAT")
A30: Days in BEAR regime | B30: =COUNTIF(Daily_Ops_Log!G4:G33,"BEAR")
A31: % of days in cash (Bear) | B31: =IFERROR(B30/30,0)
A33: RED FLAG THRESHOLDS
A34: Profit Factor >= 0.90? | B34: =IF(B17="","Awaiting data",IF(B17>=0.9,"OK - PF "&TEXT(B17,"0.00"),"WARNING: RED FLAG - PF "&TEXT(B17,"0.00")))
A35: Trailing Nifty by < 5%? | B35: =IF(B10="","Awaiting data",IF(B10>=-0.05,"OK - Alpha "&TEXT(B10*100,"0.0")&"pp","WARNING: RED FLAG - Alpha "&TEXT(B10*100,"0.0")&"pp"))
A36: Drawdown < 20%? | B36: =IF(B6=500000,"No trades yet",IF((B6-500000)/500000>-0.2,"OK — DD "&TEXT(MIN(0,(B6-500000)/500000)*-1,"0.0%"),"⚠ RED FLAG — SUSPEND TRADING"))
A38: VALIDATED BACKTEST BENCHMARKS (OOS, Policy C): PF 1.349 | CAGR +5.7% | Sharpe 0.507 | MaxDD 13.8% | Win Rate 45.2% | Alpha +5.2%/yr vs Nifty

Sheet Slippage_Tracker
A1: SLIPPAGE TRACKER — Compare simulated vs actual fills
A2: For each order placed, enter the previous close and actual fill price. Slippage auto-calculates. Target: average slippage < 0.40%. Model assumption: 0.20%.
A3: # | B3: Date | C3: Symbol | D3: Side | E3: Prev Close (Rs) | F3: Actual Fill (Rs) | G3: Qty | H3: Trade Value (Rs) | I3: Slippage % | J3: vs Model (0.20%)
A4: =IF(B4="","",ROW()-3) | H4: =IF(OR(E4="",G4=""),"",E4*G4) | I4: =IF(OR(E4="",F4=""),"",ABS(F4/E4-1)) | J4: =IF(I4="","",I4-0.002)
A5: =IF(B5="","",ROW()-3) | H5: =IF(OR(E5="",G5=""),"",E5*G5) | I5: =IF(OR(E5="",F5=""),"",ABS(F5/E5-1)) | J5: =IF(I5="","",I5-0.002)
A6: =IF(B6="","",ROW()-3) | H6: =IF(OR(E6="",G6=""),"",E6*G6) | I6: =IF(OR(E6="",F6=""),"",ABS(F6/E6-1)) | J6: =IF(I6="","",I6-0.002)
A7: =IF(B7="","",ROW()-3) | H7: =IF(OR(E7="",G7=""),"",E7*G7) | I7: =IF(OR(E7="",F7=""),"",ABS(F7/E7-1)) | J7: =IF(I7="","",I7-0.002)
A8: =IF(B8="","",ROW()-3) | H8: =IF(OR(E8="",G8=""),"",E8*G8) | I8: =IF(OR(E8="",F8=""),"",ABS(F8/E8-1)) | J8: =IF(I8="","",I8-0.002)
A9: =IF(B9="","",ROW()-3) | H9: =IF(OR(E9="",G9=""),"",E9*G9) | I9: =IF(OR(E9="",F9=""),"",ABS(F9/E9-1)) | J9: =IF(I9="","",I9-0.002)
A10: =IF(B10="","",ROW()-3) | H10: =IF(OR(E10="",G10=""),"",E10*G10) | I10: =IF(OR(E10="",F10=""),"",ABS(F10/E10-1)) | J10: =IF(I10="","",I10-0.002)
A11: =IF(B11="","",ROW()-3) | H11: =IF(OR(E11="",G11=""),"",E11*G11) | I11: =IF(OR(E11="",F11=""),"",ABS(F11/E11-1)) | J11: =IF(I11="","",I11-0.002)
A12: =IF(B12="","",ROW()-3) | H12: =IF(OR(E12="",G12=""),"",E12*G12) | I12: =IF(OR(E12="",F12=""),"",ABS(F12/E12-1)) | J12: =IF(I12="","",I12-0.002)
A13: =IF(B13="","",ROW()-3) | H13: =IF(OR(E13="",G13=""),"",E13*G13) | I13: =IF(OR(E13="",F13=""),"",ABS(F13/E13-1)) | J13: =IF(I13="","",I13-0.002)
A14: =IF(B14="","",ROW()-3) | H14: =IF(OR(E14="",G14=""),"",E14*G14) | I14: =IF(OR(E14="",F14=""),"",ABS(F14/E14-1)) | J14: =IF(I14="","",I14-0.002)
A15: =IF(B15="","",ROW()-3) | H15: =IF(OR(E15="",G15=""),"",E15*G15) | I15: =IF(OR(E15="",F15=""),"",ABS(F15/E15-1)) | J15: =IF(I15="","",I15-0.002)
... A43: =IF(B43="","",ROW()-3) | H43: =IF(OR(E43="",G43=""),"",E43*G43) | I43: =IF(OR(E43="",F43=""),"",ABS(F43/E43-1)) | J43: =IF(I43="","",I43-0.002)
A45: SLIPPAGE SUMMARY
A46: Total orders tracked | C46: =COUNTA(B4:B43)
A47: Average actual slippage % | C47: =IFERROR(AVERAGE(I4:I43),"")
A48: Maximum slippage % (single order) | C48: =IFERROR(MAX(I4:I43),"")
A49: Orders with slippage > 0.40% | C49: =COUNTIF(I4:I43,">"&0.004)
A50: Model assumption | C50: 0.002
A51: Average excess over model | C51: =IFERROR(AVERAGE(J4:J43),"")
A52: STATUS | C52: =IF(B47="","Awaiting data",IF(B47<=0.004,"OK — avg slippage within model","⚠ REVIEW — avg slippage exceeds model"))

Sheet Daily_Checklist
A1: DAILY OPERATOR CHECKLIST — Target: Under 10 minutes | Before 9:10 AM
A2: Strategy: RS=60% / EP=40% / Top-10 / Rebal 10d / SL 10% / Policy C
A4: STEP 1 — REGIME CHECK (~2 min)
A5: ☐ | B5: Open NSE website or yfinance. Get yesterday's Nifty 50 close.
A6: ☐ | B6: Calculate 50-DMA (or read from script). Enter in Daily_Ops_Log col D.
A7: ☐ | B7: Calculate 200-DMA (or read from script). Enter in Daily_Ops_Log col E.
A8: ☐ | B8: Read regime from col G (auto-classifies): BULL / FLAT / BEAR
A9: ☐ | B9: Log: Date | Nifty | 50DMA | 200DMA | Regime
A11: STEP 2 — BEAR GATE (~1 min)
A12: ☐ | B12: If BEAR AND open positions exist → place market SELL orders for ALL positions at 9:15 AM open. Record in Trade Log with Exit Reason = Regime. | C12: CRITICAL
A13: ☐ | B13: If BEAR AND no positions → hold cash. Skip to Step 5.
A14: ☐ | B14: If BULL or FLAT → proceed to Step 3.
A16: STEP 3 — STOP-LOSS CHECK (~3 min)
A17: ☐ | B17: Open Position_Log. Update col F (Current Close) for every open position.
A18: ☐ | B18: Check col K (Status). Look for *** SL TRIGGERED *** or APPROACHING SL.
A19: ☐ | B19: If SL triggered: place market SELL order for that position at 9:15 AM open.
A20: ☐ | B20: Record SL exits in Trade Log. Exit Reason = SL.
A21: ☐ | B21: Record symbol in Daily_Ops_Log col J (SL Exits Today).
A23: STEP 4 — ORDER CONFIRMATION (~2 min)
A24: ☐ | B24: Confirm all orders from yesterday are filled in broker platform.
A25: ☐ | B25: If any order is pending or partial: resolve manually. Do not place new orders.
A26: ☐ | B26: Record actual fill prices in Position_Log (not order price).
A28: STEP 5 — REBALANCE CHECK (~1 min)
A29: ☐ | B29: Check Daily_Ops_Log col L. Is today marked REBAL?
A30: ☐ | B30: If YES and regime is BULL/FLAT → run full Rebalance Checklist (separate sheet).
A31: ☐ | B31: If YES and regime is BEAR → skip rebalance. Log in Rebalance_Log as Skipped=YES.
A32: ☐ | B32: If NO → no further action needed today.
A34: STEP 6 — END-OF-DAY LOG (~1 min)
A35: ☐ | B35: Enter portfolio value in Daily_Ops_Log col H (cash + positions at close).
A36: ☐ | B36: Confirm col I shows daily P&L (auto-calculates from previous row).
A37: ☐ | B37: Add any notes in col M (data issues, manual interventions, anomalies).
A39: REGIME RULES: BULL = Nifty>200DMA AND 50DMA>200DMA | FLAT = Nifty>200DMA AND 50DMA≤200DMA | BEAR = Nifty<200DMA → CASH ONLY

Sheet Rebalance_Checklist
A1: REBALANCE-DAY CHECKLIST — Every 10th trading day from last rebalance
A2: Paper trading rebalance days: 2026-06-27 (Day 10) | 2026-07-10 (Day 20) | 2026-07-24 (Day 30)
A4: PRE-REBALANCE GATE
A5: ☐ | B5: Run Daily Checklist first (steps 1–4). Confirm regime before proceeding. | C5: Do first
A6: ☐ | B6: If BEAR regime → do NOT rebalance. Log Rebalance_Log: Skipped=YES. STOP. | C6: CRITICAL
A7: ☐ | B7: If BULL or FLAT → continue below.
A9: DATA DOWNLOAD (~3 min)
A10: ☐ | B10: Run final_validation.py (or download 134 stock closes from yfinance).
A11: ☐ | B11: Verify data: confirm 130+ stocks returned valid closes.
A12: ☐ | B12: Flag any stock with price = 0 or missing — exclude from ranking this cycle.
A14: FACTOR COMPUTATION (auto via script)
A15: ☐ | B15: Script computes RS_raw = (stock 63d return) - (Nifty 63d return) for each stock.
A16: ☐ | B16: Script computes EP_raw = max gap-day return >2% with volume >1.5x avg in 63d.
A17: ☐ | B17: Script percentile-ranks both factors (0-100). Composite = 0.60×RS + 0.40×EP.
A18: ☐ | B18: Read the top-10 stocks from script output. Paste into Rebalance_Log col E.
A20: DETERMINE TRADES (~2 min)
A21: ☐ | B21: List current holdings from Position_Log.
A22: ☐ | B22: EXITS: stocks in current holdings NOT in new top-10 → queue sell.
A23: ☐ | B23: ENTRIES: stocks in new top-10 NOT currently held → queue buy.
A24: ☐ | B24: HOLDS: stocks in both → no action.
A25: ☐ | B25: Record exits and entries in Rebalance_Log cols F and G.
A27: POSITION SIZING (~2 min)
A28: ☐ | B28: Available cash = current cash - Rs.25,000 buffer.
A29: ☐ | B29: Per-position allocation = min(available_cash ÷ N_new_entries, Rs.50,000).
A30: ☐ | B30: Shares to buy = floor(allocation ÷ yesterday's close).
A31: ☐ | B31: Verify total outlay ≤ available cash before placing orders.
A33: ORDER PLACEMENT (9:15 AM tomorrow)
A34: ☐ | B34: Place all EXIT (sell) orders first — market CNC.
A35: ☐ | B35: Wait 2 minutes.
A36: ☐ | B36: Place all ENTRY (buy) orders — market CNC. | C36: DO NOT use limit orders
A37: ☐ | B37: Record all order IDs.
A39: POST-FILL UPDATE (~3 min after 9:30 AM)
A40: ☐ | B40: Confirm all orders filled in broker platform.
A41: ☐ | B41: Record actual fill prices in Position_Log (new cost basis).
A42: ☐ | B42: Update SL level for each new entry: fill_price × 0.90 (auto-calculates).
A43: ☐ | B43: Add completed trade records to Trade_Log for each exit.
A44: ☐ | B44: Record actual fill prices in Slippage_Tracker for every buy and sell.
A45: ☐ | B45: Update Rebalance_Log: Cash Before, Cash After, Turnover %.
A46: ☐ | B46: Set next rebalance date = today + 10 trading days.

Sheet Emergency_Card
A1: WHAT TO DO IF SOMETHING BREAKS — MoneyBot RS60/EP40
A2: Print this page and keep it at your desk. Strategy is FROZEN — do not change any parameter.
A4: DATA DOWNLOAD FAILS (yfinance returns no data) | B4: 1. Retry after 30 min. 2. If still failing — SKIP rebalance (if rebal day). Do not trade on bad data. 3. Apply SL check manually using yesterday's prices (check NSEIndia.com). 4. Log the skip. Resume tomorrow.
A5: BROKER ORDER NOT PLACED (order missing from platform) | B5: 1. Do NOT retry automatically. 2. Log in to Zerodha Kite manually. 3. Verify order status. If not placed: place manually before 9:30 AM. 4. If duplicate exists: cancel duplicates immediately. 5. Record all manual actions with timestamp.
A6: STOCK OPENS BELOW SL (gap-down past stop-loss) | B6: 1. Accept the fill at the market open price. Do NOT hold hoping for recovery. 2. Record actual fill vs SL level as gap-down slippage. 3. No action on SL model unless this happens >3 times in 60 days.
A7: REGIME CLASSIFIED WRONG (you entered wrong DMA values) | B7: Bear→Bull error (invested when should be in cash): → Exit ALL positions at next open. Do not make back Bear regime days. Bull→Bear error (in cash when should be invested): → Wait until next rebalance. Do not chase missed entry. → Log the error and root cause.
A8: CORPORATE ACTION (split, bonus, merger, delisting) | B8: Split / Bonus: Adjust cost basis (new = old ÷ ratio). Adjust qty and SL. Merger / Delisting: Exit at next open. Remove from universe list. Rights issue: Do not subscribe. SL check handles price impact.
A9: PORTFOLIO DOWN >20% FROM PEAK [CRITICAL — AUTO-SHUTDOWN TRIGGER] | B9: 1. EXIT ALL positions at next open. No exceptions. 2. Stop all trading for 30 calendar days. 3. During pause: run deployment_verification.py on latest 2-year data. → Fresh OOS PF >1.10: resume after 30 days. → Fresh OOS PF <1.05: do NOT resume. Full re-validation required. 4. Do not shorten the 30-day pause even if market recovers.
A10: 3 CONSECUTIVE LOSING REBALANCES | B10: 1. Do NOT stop trading. This is within normal variance. 2. Compute rolling 30-day PF from Trade_Log. → PF >0.85: continue. Log the flag. → PF <0.85: raise red flag. Run deployment_verification.py. 3. Do NOT change strategy parameters based on a losing streak.
A11: MARKET-WIDE CIRCUIT BREAKER (SEBI halts trading) | B11: 1. Do not place any orders during market halt. 2. Wait for normal trading to resume. 3. On next trading day: run full Daily Checklist from Step 1. 4. SL and regime checks take priority over everything else.
A12: PERMANENT RULES — NEVER VIOLATE
A13: ⛔ | B13: Do NOT trade in Bear regime (Nifty < 200DMA).
A14: ⛔ | B14: Do NOT change RS/EP weights, Top-N, SL%, or rebalance cadence without full re-validation.
A15: ⛔ | B15: Do NOT use limit orders — strategy is modelled on market fills.
A16: ⛔ | B16: Do NOT trade on bad or stale data — skip the day and log it.
A17: ⛔ | B17: Do NOT reduce the 30-day suspension after a >20% drawdown.
A19: STRATEGY FROZEN: RS=60% | EP=40% | Top-10 | Rebal 10d | SL 10% | Policy C || CURRENT STATE (Jun 2026): BEAR — hold cash — re-entry when Nifty > 200DMA || VALIDATED OOS: PF 1.349 | CAGR +5.7% | Sharpe 0.507 | MaxDD 13.8%
